{
  "table": [
    {
      "idStanding": "75564",
      "intRank": "11",
      "idTeam": "134474",
      "strTeam": "Newcastle Jets",
      "strTeamBadge": "https://www.thesportsdb.com/images/media/team/badge/qrxusv1473454594.png/tiny",
      "idLeague": "4356",
      "strLeague": "Australian A-League",
      "strSeason": "2020-2021",
      "strForm": "LLWDW",
      "strDescription": "",
      "intPlayed": "11",
      "intWin": "3",
      "intLoss": "6",
      "intDraw": "2",
      "intGoalsFor": "9",
      "intGoalsAgainst": "13",
      "intGoalDifference": "-4",
      "intPoints": "11",
      "dateUpdated": "2021-03-08 23:00:16"
    },
    {
      "idStanding": "75563",
      "intRank": "10",
      "idTeam": "134475",
      "strTeam": "Wellington Phoenix",
      "strTeamBadge": "https://www.thesportsdb.com/images/media/team/badge/oegi471515786300.png/tiny",
      "idLeague": "4356",
      "strLeague": "Australian A-League",
      "strSeason": "2020-2021",
      "strForm": "WWLDL",
      "strDescription": "",
      "intPlayed": "10",
      "intWin": "3",
      "intLoss": "5",
      "intDraw": "2",
      "intGoalsFor": "13",
      "intGoalsAgainst": "14",
      "intGoalDifference": "-1",
      "intPoints": "11",
      "dateUpdated": "2021-03-08 23:00:16"
    },
    {
      "idStanding": "75562",
      "intRank": "9",
      "idTeam": "137542",
      "strTeam": "Western United FC",
      "strTeamBadge": "https://www.thesportsdb.com/images/media/team/badge/q8lpcc1577967815.png/tiny",
      "idLeague": "4356",
      "strLeague": "Australian A-League",
      "strSeason": "2020-2021",
      "strForm": "LWWLD",
      "strDescription": "",
      "intPlayed": "8",
      "intWin": "3",
      "intLoss": "3",
      "intDraw": "2",
      "intGoalsFor": "16",
      "intGoalsAgainst": "14",
      "intGoalDifference": "2",
      "intPoints": "11",
      "dateUpdated": "2021-03-08 23:00:16"
    },
    {
      "idStanding": "75561",
      "intRank": "8",
      "idTeam": "134473",
      "strTeam": "Sydney FC",
      "strTeamBadge": "https://www.thesportsdb.com/images/media/team/badge/utgq8z1546110747.png/tiny",
      "idLeague": "4356",
      "strLeague": "Australian A-League",
      "strSeason": "2020-2021",
      "strForm": "DLLDW",
      "strDescription": "",
      "intPlayed": "9",
      "intWin": "3",
      "intLoss": "3",
      "intDraw": "3",
      "intGoalsFor": "11",
      "intGoalsAgainst": "10",
      "intGoalDifference": "1",
      "intPoints": "12",
      "dateUpdated": "2021-03-08 23:00:16"
    },
    {
      "idStanding": "75560",
      "intRank": "7",
      "idTeam": "134481",
      "strTeam": "Perth Glory",
      "strTeamBadge": "https://www.thesportsdb.com/images/media/team/badge/qmx19q1546110444.png/tiny",
      "idLeague": "4356",
      "strLeague": "Australian A-League",
      "strSeason": "2020-2021",
      "strForm": "LLWWW",
      "strDescription": "",
      "intPlayed": "8",
      "intWin": "4",
      "intLoss": "4",
      "intDraw": "0",
      "intGoalsFor": "19",
      "intGoalsAgainst": "18",
      "intGoalDifference": "1",
      "intPoints": "12",
      "dateUpdated": "2021-03-08 23:00:16"
    },
    {
      "idStanding": "75559",
      "intRank": "6",
      "idTeam": "134476",
      "strTeam": "Brisbane Roar FC",
      "strTeamBadge": "https://www.thesportsdb.com/images/media/team/badge/sypxsu1473454634.png/tiny",
      "idLeague": "4356",
      "strLeague": "Australian A-League",
      "strSeason": "2020-2021",
      "strForm": "DLDDL",
      "strDescription": "Final Series Play-offs",
      "intPlayed": "10",
      "intWin": "4",
      "intLoss": "3",
      "intDraw": "3",
      "intGoalsFor": "15",
      "intGoalsAgainst": "12",
      "intGoalDifference": "3",
      "intPoints": "15",
      "dateUpdated": "2021-03-08 23:00:16"
    },
    {
      "idStanding": "75558",
      "intRank": "5",
      "idTeam": "134634",
      "strTeam": "Melbourne City FC",
      "strTeamBadge": "https://www.thesportsdb.com/images/media/team/badge/rkeqme1603301840.png/tiny",
      "idLeague": "4356",
      "strLeague": "Australian A-League",
      "strSeason": "2020-2021",
      "strForm": "WWWLL",
      "strDescription": "Final Series Play-offs",
      "intPlayed": "9",
      "intWin": "5",
      "intLoss": "4",
      "intDraw": "0",
      "intGoalsFor": "17",
      "intGoalsAgainst": "12",
      "intGoalDifference": "5",
      "intPoints": "15",
      "dateUpdated": "2021-03-08 23:00:16"
    },
    {
      "idStanding": "75557",
      "intRank": "4",
      "idTeam": "134472",
      "strTeam": "Adelaide United",
      "strTeamBadge": "https://www.thesportsdb.com/images/media/team/badge/wpyuwv1473454602.png/tiny",
      "idLeague": "4356",
      "strLeague": "Australian A-League",
      "strSeason": "2020-2021",
      "strForm": "WWWLL",
      "strDescription": "Final Series Play-offs",
      "intPlayed": "10",
      "intWin": "5",
      "intLoss": "4",
      "intDraw": "1",
      "intGoalsFor": "16",
      "intGoalsAgainst": "19",
      "intGoalDifference": "-3",
      "intPoints": "16",
      "dateUpdated": "2021-03-08 23:00:16"
    },
    {
      "idStanding": "75556",
      "intRank": "3",
      "idTeam": "134480",
      "strTeam": "Western Sydney Wanderers FC",
      "strTeamBadge": "https://www.thesportsdb.com/images/media/team/badge/ej3zmf1603301820.png/tiny",
      "idLeague": "4356",
      "strLeague": "Australian A-League",
      "strSeason": "2020-2021",
      "strForm": "WLLDW",
      "strDescription": "Final Series Play-offs",
      "intPlayed": "11",
      "intWin": "4",
      "intLoss": "3",
      "intDraw": "4",
      "intGoalsFor": "14",
      "intGoalsAgainst": "13",
      "intGoalDifference": "1",
      "intPoints": "16",
      "dateUpdated": "2021-03-08 23:00:16"
    },
    {
      "idStanding": "75555",
      "intRank": "2",
      "idTeam": "138063",
      "strTeam": "Macarthur FC",
      "strTeamBadge": "https://www.thesportsdb.com/images/media/team/badge/9gr66g1579348350.png/tiny",
      "idLeague": "4356",
      "strLeague": "Australian A-League",
      "strSeason": "2020-2021",
      "strForm": "LWLWW",
      "strDescription": "Final Series",
      "intPlayed": "11",
      "intWin": "5",
      "intLoss": "4",
      "intDraw": "2",
      "intGoalsFor": "14",
      "intGoalsAgainst": "15",
      "intGoalDifference": "-1",
      "intPoints": "17",
      "dateUpdated": "2021-03-08 23:00:16"
    },
    {
      "idStanding": "75554",
      "intRank": "1",
      "idTeam": "134479",
      "strTeam": "Central Coast Mariners",
      "strTeamBadge": "https://www.thesportsdb.com/images/media/team/badge/16igq81547381432.png/tiny",
      "idLeague": "4356",
      "strLeague": "Australian A-League",
      "strSeason": "2020-2021",
      "strForm": "WWLWW",
      "strDescription": "Final Series",
      "intPlayed": "11",
      "intWin": "8",
      "intLoss": "3",
      "intDraw": "0",
      "intGoalsFor": "20",
      "intGoalsAgainst": "11",
      "intGoalDifference": "9",
      "intPoints": "24",
      "dateUpdated": "2021-03-08 23:00:16"
    },
    {
      "idStanding": "75565",
      "intRank": "12",
      "idTeam": "134477",
      "strTeam": "Melbourne Victory",
      "strTeamBadge": "https://www.thesportsdb.com/images/media/team/badge/wwvsqx1473454564.png/tiny",
      "idLeague": "4356",
      "strLeague": "Australian A-League",
      "strSeason": "2020-2021",
      "strForm": "LLWLL",
      "strDescription": "",
      "intPlayed": "10",
      "intWin": "2",
      "intLoss": "7",
      "intDraw": "1",
      "intGoalsFor": "10",
      "intGoalsAgainst": "23",
      "intGoalDifference": "-13",
      "intPoints": "7",
      "dateUpdated": "2021-03-08 23:00:16"
    }
  ]
}